technote/__init__.py
technote/factory.py
technote/main.py
technote/py.typed
technote/sphinxconf.py
technote/ext/__init__.py
technote/ext/abstract.py
technote/ext/insertposttitle.py
technote/ext/metadata.py
technote/ext/pygmentscss.py
technote/ext/toc.py
technote/ext/wraptables.py
technote/ext/templates/post-title.html.jinja
technote/metadata/__init__.py
technote/metadata/licenses.json
technote/metadata/model.py
technote/metadata/orcid.py
technote/metadata/ror.py
technote/metadata/spdx.py
technote/metadata/zenodo.py
technote/sources/__init__.py
technote/sources/tomlsettings.py
technote/templating/__init__.py
technote/templating/context.py
technote/templating/highwire.py
technote/templating/metatagbase.py
technote/templating/opengraph.py
technote/theme/defindex.html
technote/theme/domainindex.html
technote/theme/genindex-single.html
technote/theme/genindex-split.html
technote/theme/genindex.html
technote/theme/globaltoc.html
technote/theme/layout.html
technote/theme/localtoc.html
technote/theme/page.html
technote/theme/relations.html
technote/theme/search.html
technote/theme/searchbox.html
technote/theme/sourcelink.html
technote/theme/theme.conf
technote/theme/changes/frameset.html
technote/theme/changes/rstsource.html
technote/theme/changes/versionchanges.html
technote/theme/components/breadcrumbs.html
technote/theme/components/edit-this-page.html
technote/theme/components/logo.html
technote/theme/components/related-pages.html
technote/theme/components/search-hide.html
technote/theme/components/search-input.html
technote/theme/components/sidebar-authors.html
technote/theme/components/sidebar-logo.html
technote/theme/components/sidebar-source.html
technote/theme/components/sidebar-toc.html
technote/theme/components/sidebar-version.html
technote/theme/components/toggle-sidebar-primary.html
technote/theme/components/toggle-sidebar-secondary.html
technote/theme/components/view-this-page.html
technote/theme/partials/octicons.html
technote/theme/sections/announcement.html
technote-0.9.1.dist-info/licenses/LICENSE
technote-0.9.1.dist-info/METADATA
technote-0.9.1.dist-info/WHEEL
technote-0.9.1.dist-info/entry_points.txt
technote-0.9.1.dist-info/top_level.txt
technote-0.9.1.dist-info/RECORD
