Metadata-Version: 2.4
Name: technote
Version: 0.9.1
Summary: Rubin Observatory's framework for Sphinx-based technote documents.
License-Expression: MIT
Project-URL: Homepage, https://technote.lsst.io
Project-URL: Source, https://github.com/lsst-sqre/technote
Keywords: rubin,lsst
Classifier: Development Status :: 4 - Beta
Classifier: Programming Language :: Python
Classifier: Programming Language :: Python :: 3
Classifier: Programming Language :: Python :: 3.11
Classifier: Programming Language :: Python :: 3.12
Classifier: Intended Audience :: Developers
Classifier: Natural Language :: English
Classifier: Operating System :: POSIX
Classifier: Typing :: Typed
Requires-Python: >=3.11
License-File: LICENSE
Requires-Dist: Sphinx
Requires-Dist: sphinx-basic-ng>=1.0.0b1
Requires-Dist: base32-lib
Requires-Dist: pydantic[email]>=2.0.0
Requires-Dist: beautifulsoup4
Requires-Dist: pygments
Requires-Dist: accessible-pygments
Requires-Dist: myst-parser
Requires-Dist: markdown-it-py[linkify]
Provides-Extra: dev
Requires-Dist: coverage[toml]; extra == "dev"
Requires-Dist: pytest<8.0; extra == "dev"
Requires-Dist: pytest-asyncio; extra == "dev"
Requires-Dist: pre-commit; extra == "dev"
Requires-Dist: mypy; extra == "dev"
Requires-Dist: types-docutils; extra == "dev"
Requires-Dist: defusedxml; extra == "dev"
Requires-Dist: lxml; extra == "dev"
Requires-Dist: cssselect; extra == "dev"
Requires-Dist: mf2py; extra == "dev"
Dynamic: license-file
